sddn/__info__.py
sddn/__init__.py
sddn/discrete_distribution.py
sddn/sddn_utils.py
sddn-0.0.2.dist-info/METADATA
sddn-0.0.2.dist-info/WHEEL
sddn-0.0.2.dist-info/top_level.txt
sddn-0.0.2.dist-info/RECORD
