Metadata-Version: 2.4
Name: sddn
Version: 0.0.2
Summary: sddn
Home-page: https://github.com/DIYer22/sddn
Author: DIYer22
Author-email: ylxx@live.com
Classifier: Topic :: Software Development :: Libraries :: Python Modules
Classifier: Programming Language :: Python :: 3
Classifier: License :: OSI Approved :: MIT License
Classifier: Operating System :: OS Independent
Requires-Dist: boxx
Dynamic: author
Dynamic: author-email
Dynamic: classifier
Dynamic: description
Dynamic: description-content-type
Dynamic: home-page
Dynamic: requires-dist
Dynamic: summary
